ordeq_pandas/__init__.py
ordeq_pandas/_version.py
ordeq_pandas/csv.py
ordeq_pandas/excel.py
ordeq_pandas/parquet.py
ordeq_pandas/py.typed
ordeq_pandas-1.0.1.dist-info/licenses/LICENSE
ordeq_pandas-1.0.1.dist-info/METADATA
ordeq_pandas-1.0.1.dist-info/WHEEL
ordeq_pandas-1.0.1.dist-info/top_level.txt
ordeq_pandas-1.0.1.dist-info/RECORD
